setup.cfg
setup.py
earl/__init__.py
earl.egg-info/PKG-INFO
earl.egg-info/SOURCES.txt
earl.egg-info/dependency_links.txt
earl.egg-info/entry_points.txt
earl.egg-info/top_level.txt
earl.egg-info/zip-safe