Metadata-Version: 1.0
Name: earl
Version: 0.1.dev0
Summary: Tool for manipulating URL quea
Home-page: https://github.com/infin8/earl.py
Author: n8
Author-email: yo.its.n8@gmail.com
License: MIT
Keywords: url
Platform: UNKNOWN
